{"EndUserIp":"182.156.5.54","ResultIndex":"8","TraceId":"ebcf7ce5-5e56-4959-9bff-9e88bd483e6a","TokenId":"15977ecc-c150-408c-a5e3-4819bfe53c60","BoardingPointId":"1","DropingPointId":"14","Passenger":[{"LeadPassenger":"true","PassengerId":0,"Title":"1","Address":"test address","Email":"poovarasanprovab@gmail.com","Age":26,"FirstName":"poovarasan","LastName":"Govindaraju","Gender":"1","IdNumber":"","IdType":"","Phoneno":"9025902577","Seat":{"ColumnNo":"000","Height":2,"IsLadiesSeat":false,"IsMalesSeat":false,"IsUpper":false,"RowNo":"000","SeatFare":786.45,"SeatIndex":27,"SeatName":"L2","SeatStatus":true,"SeatType":2,"Width":1,"Price":{"CurrencyCode":"INR","BasePrice":786.45,"Tax":0,"OtherCharges":0,"Discount":0,"PublishedPrice":786.45,"PublishedPriceRoundedOff":786,"OfferedPrice":739.26,"OfferedPriceRoundedOff":739,"AgentCommission":47.19,"AgentMarkUp":0,"TDS":2.36,"GST":{"CGSTAmount":0,"CGSTRate":0,"CessAmount":0,"CessRate":0,"IGSTAmount":0,"IGSTRate":18,"SGSTAmount":0,"SGSTRate":0,"TaxableAmount":0}}}}]}