{"BlockResult":{"IsPriceChanged":false,"ResponseStatus":1,"Error":{"ErrorCode":0,"ErrorMessage":""},"ArrivalTime":"03\/21\/2024 05:00:00","BusType":"Volvo A\/C Seater (1+1)","DepartureTime":"03\/20\/2024 16:14:00","ServiceName":"Seat Seller","TraceId":"edac0224-fb2b-4e40-9064-78db9a714904","TravelName":"TESTING ACCOUNT","BoardingPointdetails":{"CityPointAddress":"tuk","CityPointContactNumber":"1234567890","CityPointIndex":1,"CityPointLandmark":"sdad","CityPointLocation":"Domlur","CityPointName":"CV Dasarahalli","CityPointTime":"2024-03-20T16:14:00"},"CancelPolicy":[{"CancellationCharge":10,"CancellationChargeType":2,"PolicyString":"Till 11:14 on 19 Mar 2024","TimeBeforeDept":"29$-1","FromDate":"2024-03-12T16:50:41","ToDate":"2024-03-19T11:14:00"},{"CancellationCharge":50,"CancellationChargeType":2,"PolicyString":"Between 11:14 on 19 Mar 2024 - 23:14 on 19 Mar 2024","TimeBeforeDept":"17$29","FromDate":"2024-03-19T11:14:00","ToDate":"2024-03-19T23:14:00"},{"CancellationCharge":100,"CancellationChargeType":2,"PolicyString":"After 23:14 on 19 Mar 2024","TimeBeforeDept":"0$17","FromDate":"2024-03-19T23:14:00","ToDate":"2024-03-21T05:00:00"}],"DropingPointdetails":{"CityPointIndex":1,"CityPointLocation":"Afzal Gunj","CityPointName":"Afzal Gunj","CityPointTime":"2024-03-21T05:00:00"},"Passenger":[{"LeadPassenger":true,"Title":"1","Address":"test address","Age":26,"City":null,"Email":"anil.kumar@provabmail.com","FirstName":"Anil","Gender":1,"IdNumber":"","IdType":"","LastName":"Kumar","Phoneno":"9879876548","Seat":{"ColumnNo":"000","Height":1,"IsLadiesSeat":false,"IsMalesSeat":false,"IsUpper":false,"RowNo":"000","SeatFare":10.50,"SeatIndex":1,"SeatName":"1","SeatStatus":true,"SeatType":1,"Width":1,"Price":{"CurrencyCode":"INR","BasePrice":10.50,"Tax":0,"OtherCharges":0,"Discount":0,"PublishedPrice":10.50,"PublishedPriceRoundedOff":11,"OfferedPrice":-19.50,"OfferedPriceRoundedOff":-20,"AgentCommission":30.00,"AgentMarkUp":0,"TDS":12.00,"GST":{"CGSTAmount":0,"CGSTRate":0,"CessAmount":0,"CessRate":0,"IGSTAmount":0,"IGSTRate":18,"SGSTAmount":0,"SGSTRate":0,"TaxableAmount":0}}},"State":null}]}}