{"BlockResult":{"IsPriceChanged":false,"ResponseStatus":1,"Error":{"ErrorCode":0,"ErrorMessage":""},"ArrivalTime":"03\/29\/2024 22:00:00","BusType":"Isuzu A\/C Seater\/Sleeper Executive Luxury (1+1)","DepartureTime":"03\/29\/2024 10:00:00","ServiceName":"Seat Seller","TraceId":"6672c778-d60b-48a5-9ca8-c1e535492f46","TravelName":"TESTING ACCOUNT","BoardingPointdetails":{"CityPointAddress":"hal","CityPointContactNumber":"64535425255","CityPointIndex":1,"CityPointLandmark":"hal","CityPointLocation":"HAL Main Gate","CityPointName":"HAL Main Gate (Pickup Bus)","CityPointTime":"2024-03-29T10:00:00"},"CancelPolicy":[{"CancellationCharge":10,"CancellationChargeType":2,"PolicyString":"Till 05:00 on 28 Mar 2024","TimeBeforeDept":"29$-1","FromDate":"2024-03-12T15:20:46","ToDate":"2024-03-28T05:00:00"},{"CancellationCharge":50,"CancellationChargeType":2,"PolicyString":"Between 05:00 on 28 Mar 2024 - 17:00 on 28 Mar 2024","TimeBeforeDept":"17$29","FromDate":"2024-03-28T05:00:00","ToDate":"2024-03-28T17:00:00"},{"CancellationCharge":100,"CancellationChargeType":2,"PolicyString":"After 17:00 on 28 Mar 2024","TimeBeforeDept":"0$17","FromDate":"2024-03-28T17:00:00","ToDate":"2024-03-29T22:00:00"}],"DropingPointdetails":{"CityPointIndex":1,"CityPointLocation":"AFZALGUNJ  (VAN PICKUP)","CityPointName":"AFZALGUNJ  (VAN PICKUP) (Pickup Bus)","CityPointTime":"2024-03-29T22:00:00"},"Passenger":[{"LeadPassenger":true,"Title":"Mr","Address":"test address","Age":10,"City":null,"Email":"supervision@provab.com","FirstName":"test","Gender":0,"IdNumber":"","IdType":"","LastName":"t","Phoneno":"98746321","Seat":{"ColumnNo":"002","Height":1,"IsLadiesSeat":false,"IsMalesSeat":false,"IsUpper":true,"RowNo":"003","SeatFare":73.50,"SeatIndex":31,"SeatName":"d","SeatStatus":true,"SeatType":1,"Width":1,"Price":{"CurrencyCode":"INR","BasePrice":73.50,"Tax":0,"OtherCharges":0,"Discount":0,"PublishedPrice":73.50,"PublishedPriceRoundedOff":74,"OfferedPrice":43.50,"OfferedPriceRoundedOff":44,"AgentCommission":30.00,"AgentMarkUp":0,"TDS":12.00,"GST":{"CGSTAmount":0,"CGSTRate":0,"CessAmount":0,"CessRate":0,"IGSTAmount":0,"IGSTRate":18,"SGSTAmount":0,"SGSTRate":0,"TaxableAmount":0}}},"State":null},{"LeadPassenger":false,"Title":"Mr","Address":"","Age":25,"City":null,"Email":"supervision@provab.com","FirstName":"sathis","Gender":0,"IdNumber":"","IdType":"","LastName":"kumar","Phoneno":"98746321","Seat":{"ColumnNo":"003","Height":1,"IsLadiesSeat":false,"IsMalesSeat":false,"IsUpper":true,"RowNo":"003","SeatFare":73.50,"SeatIndex":32,"SeatName":"f","SeatStatus":true,"SeatType":1,"Width":1,"Price":{"CurrencyCode":"INR","BasePrice":73.50,"Tax":0,"OtherCharges":0,"Discount":0,"PublishedPrice":73.50,"PublishedPriceRoundedOff":74,"OfferedPrice":43.50,"OfferedPriceRoundedOff":44,"AgentCommission":30.00,"AgentMarkUp":0,"TDS":12.00,"GST":{"CGSTAmount":0,"CGSTRate":0,"CessAmount":0,"CessRate":0,"IGSTAmount":0,"IGSTRate":18,"SGSTAmount":0,"SGSTRate":0,"TaxableAmount":0}}},"State":null}]}}