{"EndUserIp":"14.97.94.42","ResultIndex":"8","TraceId":"6b1d0d51-cfef-4212-a0fd-85e9764fbc8e","TokenId":"6ac98515-27e3-487d-bb2a-cbbc6b4e5256","BoardingPointId":"1","DropingPointId":"1","Passenger":[{"LeadPassenger":true,"Title":"1","Address":"test address","Age":30,"City":null,"Email":"anilkumarn.provab@gmail.com","FirstName":"Anil","Gender":1,"IdNumber":"","IdType":"","LastName":"Kumar","Phoneno":"7894561230","Seat":{"ColumnNo":"005","Height":1,"IsLadiesSeat":false,"IsMalesSeat":false,"IsUpper":false,"RowNo":"002","SeatFare":5.25,"SeatIndex":16,"SeatName":"16","SeatStatus":true,"SeatType":1,"Width":1,"Price":{"CurrencyCode":"INR","BasePrice":5.25,"Tax":0,"OtherCharges":0,"Discount":0,"PublishedPrice":5.25,"PublishedPriceRoundedOff":5,"OfferedPrice":-24.75,"OfferedPriceRoundedOff":-25,"AgentCommission":30,"AgentMarkUp":0,"TDS":12,"GST":{"CGSTAmount":0,"CGSTRate":0,"CessAmount":0,"CessRate":0,"IGSTAmount":0,"IGSTRate":18,"SGSTAmount":0,"SGSTRate":0,"TaxableAmount":0}}},"State":null},{"LeadPassenger":false,"Title":"1","Address":"","Age":25,"City":null,"Email":"anilkumarn.provab@gmail.com","FirstName":"Poovasarasan","Gender":1,"IdNumber":"","IdType":"","LastName":"Provab","Phoneno":"9856741253","Seat":{"ColumnNo":"006","Height":1,"IsLadiesSeat":false,"IsMalesSeat":false,"IsUpper":false,"RowNo":"002","SeatFare":5.25,"SeatIndex":17,"SeatName":"17","SeatStatus":true,"SeatType":1,"Width":1,"Price":{"CurrencyCode":"INR","BasePrice":5.25,"Tax":0,"OtherCharges":0,"Discount":0,"PublishedPrice":5.25,"PublishedPriceRoundedOff":5,"OfferedPrice":-24.75,"OfferedPriceRoundedOff":-25,"AgentCommission":30,"AgentMarkUp":0,"TDS":12,"GST":{"CGSTAmount":0,"CGSTRate":0,"CessAmount":0,"CessRate":0,"IGSTAmount":0,"IGSTRate":18,"SGSTAmount":0,"SGSTRate":0,"TaxableAmount":0}}},"State":null}]}