{"BusSearchResult":{"ResponseStatus":1,"Error":{"ErrorCode":0,"ErrorMessage":""},"Destination":"Chennai","Origin":"Bangalore","TraceId":"e5e5026f-8748-4653-a3d6-2b47163bb64f","BusResults":[{"ResultIndex":8,"ArrivalTime":"2024-08-31T06:00:00","AvailableSeats":36,"DepartureTime":"2024-08-30T23:25:00","RouteId":"5000002149902340981","BusType":"Volvo Multi-Axle A\/C Sleeper (2+1)","ServiceName":"Seat Seller","TravelName":"SRS Travels","IdProofRequired":false,"IsDropPointMandatory":false,"LiveTrackingAvailable":false,"MTicketEnabled":true,"MaxSeatsPerTicket":6,"OperatorId":22,"PartialCancellationAllowed":true,"BoardingPointsDetails":[{"CityPointIndex":1,"CityPointLocation":"Majestic Ananda Rao Circle","CityPointName":"Anand Rao Circle","CityPointTime":"2024-08-30T22:30:00"},{"CityPointIndex":2,"CityPointLocation":"Kalasipalyam","CityPointName":"Kalasipalyam","CityPointTime":"2024-08-30T23:00:00"},{"CityPointIndex":3,"CityPointLocation":"Wilsongarden","CityPointName":"Wilson Garden","CityPointTime":"2024-08-30T23:10:00"},{"CityPointIndex":4,"CityPointLocation":"Dairy Circle","CityPointName":"Dairy Circle","CityPointTime":"2024-08-30T23:15:00"},{"CityPointIndex":5,"CityPointLocation":"St. Johns Hospital","CityPointName":"Madiwala","CityPointTime":"2024-08-30T23:20:00"},{"CityPointIndex":6,"CityPointLocation":"Madiwala","CityPointName":"Madiwala","CityPointTime":"2024-08-30T23:25:00"},{"CityPointIndex":7,"CityPointLocation":"Silk Board Towards Madiwala Police station & Darga","CityPointName":"Silk Board","CityPointTime":"2024-08-30T23:30:00"},{"CityPointIndex":8,"CityPointLocation":"Electonic City Toll Gate","CityPointName":"Singasandra","CityPointTime":"2024-08-30T23:35:00"},{"CityPointIndex":9,"CityPointLocation":"Bommsandra SRS Travels ","CityPointName":"Others","CityPointTime":"2024-08-30T23:40:00"},{"CityPointIndex":10,"CityPointLocation":"Attibele Toll","CityPointName":"Attibele","CityPointTime":"2024-08-30T23:45:00"}],"DroppingPointsDetails":[{"CityPointIndex":1,"CityPointLocation":"Koyembedu","CityPointName":"Koyambedu","CityPointTime":"2024-08-31T06:00:00"},{"CityPointIndex":2,"CityPointLocation":"Guindy subway","CityPointName":"Guindy","CityPointTime":"2024-08-31T06:30:00"},{"CityPointIndex":3,"CityPointLocation":"Mathiyakailash","CityPointName":"Madhya Kailash","CityPointTime":"2024-08-31T06:40:00"},{"CityPointIndex":4,"CityPointLocation":"Tidel Park","CityPointName":"Tidel Park","CityPointTime":"2024-08-31T06:50:00"},{"CityPointIndex":5,"CityPointLocation":"SRB Tools","CityPointName":"SRP Tools","CityPointTime":"2024-08-31T06:55:00"},{"CityPointIndex":6,"CityPointLocation":"Kandhanchavadi Bus Stop","CityPointName":"Perungudi","CityPointTime":"2024-08-31T07:00:00"},{"CityPointIndex":7,"CityPointLocation":"Perungudi","CityPointName":"Perungudi","CityPointTime":"2024-08-31T07:05:00"},{"CityPointIndex":8,"CityPointLocation":"Thoraipakkam","CityPointName":"Thuraipakkam","CityPointTime":"2024-08-31T07:10:00"},{"CityPointIndex":9,"CityPointLocation":"Karapakkam.","CityPointName":"Karappakkam","CityPointTime":"2024-08-31T07:15:00"},{"CityPointIndex":10,"CityPointLocation":"Sholinganallur ","CityPointName":"Sholinganallur","CityPointTime":"2024-08-31T07:20:00"}],"BusPrice":{"CurrencyCode":"INR","BasePrice":1150.00,"Tax":0,"OtherCharges":0,"Discount":0,"PublishedPrice":1150.00,"PublishedPriceRoundedOff":1150,"OfferedPrice":1081.00,"OfferedPriceRoundedOff":1081,"AgentCommission":69.00,"AgentMarkUp":0,"TDS":3.45,"GST":{"CGSTAmount":0,"CGSTRate":0,"CessAmount":0,"CessRate":0,"IGSTAmount":0,"IGSTRate":18,"SGSTAmount":0,"SGSTRate":0,"TaxableAmount":0}},"CancellationPolicies":[{"CancellationCharge":15,"CancellationChargeType":2,"PolicyString":"Till 11:25 on 23 Aug 2024","TimeBeforeDept":"180$-1","FromDate":"2024-07-02T15:29:59","ToDate":"2024-08-23T11:25:00"},{"CancellationCharge":15,"CancellationChargeType":2,"PolicyString":"Between 11:25 on 23 Aug 2024 - 11:25 on 29 Aug 2024","TimeBeforeDept":"36$180","FromDate":"2024-08-23T11:25:00","ToDate":"2024-08-29T11:25:00"},{"CancellationCharge":20,"CancellationChargeType":2,"PolicyString":"Between 11:25 on 29 Aug 2024 - 23:25 on 29 Aug 2024","TimeBeforeDept":"24$36","FromDate":"2024-08-29T11:25:00","ToDate":"2024-08-29T23:25:00"},{"CancellationCharge":50,"CancellationChargeType":2,"PolicyString":"Between 23:25 on 29 Aug 2024 - 07:25 on 30 Aug 2024","TimeBeforeDept":"16$24","FromDate":"2024-08-29T23:25:00","ToDate":"2024-08-30T07:25:00"},{"CancellationCharge":100,"CancellationChargeType":2,"PolicyString":"After 07:25 on 30 Aug 2024","TimeBeforeDept":"0$16","FromDate":"2024-08-30T07:25:00","ToDate":"2024-08-31T06:00:00"}]},{"ResultIndex":1,"ArrivalTime":"2024-08-31T06:00:00","AvailableSeats":30,"DepartureTime":"2024-08-30T23:00:00","RouteId":"1000002149900327277","BusType":"NON A\/C Sleeper (2+1)","ServiceName":"Seat Seller","TravelName":"SRS Travels","IdProofRequired":false,"IsDropPointMandatory":false,"LiveTrackingAvailable":false,"MTicketEnabled":true,"MaxSeatsPerTicket":6,"OperatorId":22,"PartialCancellationAllowed":true,"BoardingPointsDetails":[{"CityPointIndex":1,"CityPointLocation":"Majestic Ananda Rao Circle (Pickup Van\/Bus)","CityPointName":"Anand Rao Circle","CityPointTime":"2024-08-30T21:15:00"},{"CityPointIndex":2,"CityPointLocation":"Kalasipalyam","CityPointName":"Kalasipalyam","CityPointTime":"2024-08-30T22:15:00"},{"CityPointIndex":3,"CityPointLocation":"Wilsongarden","CityPointName":"Wilson Garden","CityPointTime":"2024-08-30T22:30:00"},{"CityPointIndex":4,"CityPointLocation":"Madiwala","CityPointName":"Madiwala","CityPointTime":"2024-08-30T23:00:00"},{"CityPointIndex":5,"CityPointLocation":"Bommsandra SRS Travels ","CityPointName":"Others","CityPointTime":"2024-08-30T23:25:00"}],"DroppingPointsDetails":[{"CityPointIndex":1,"CityPointLocation":"Koyambedu ","CityPointName":"Koyambedu","CityPointTime":"2024-08-31T06:00:00"}],"BusPrice":{"CurrencyCode":"INR","BasePrice":1400.00,"Tax":0,"OtherCharges":0,"Discount":0,"PublishedPrice":1400.00,"PublishedPriceRoundedOff":1400,"OfferedPrice":1316.00,"OfferedPriceRoundedOff":1316,"AgentCommission":84.00,"AgentMarkUp":0,"TDS":4.20,"GST":{"CGSTAmount":0,"CGSTRate":0,"CessAmount":0,"CessRate":0,"IGSTAmount":0,"IGSTRate":18,"SGSTAmount":0,"SGSTRate":0,"TaxableAmount":0}},"CancellationPolicies":[{"CancellationCharge":15,"CancellationChargeType":2,"PolicyString":"Till 11:00 on 23 Aug 2024","TimeBeforeDept":"180$-1","FromDate":"2024-07-02T15:29:59","ToDate":"2024-08-23T11:00:00"},{"CancellationCharge":15,"CancellationChargeType":2,"PolicyString":"Between 11:00 on 23 Aug 2024 - 11:00 on 29 Aug 2024","TimeBeforeDept":"36$180","FromDate":"2024-08-23T11:00:00","ToDate":"2024-08-29T11:00:00"},{"CancellationCharge":20,"CancellationChargeType":2,"PolicyString":"Between 11:00 on 29 Aug 2024 - 23:00 on 29 Aug 2024","TimeBeforeDept":"24$36","FromDate":"2024-08-29T11:00:00","ToDate":"2024-08-29T23:00:00"},{"CancellationCharge":50,"CancellationChargeType":2,"PolicyString":"Between 23:00 on 29 Aug 2024 - 07:00 on 30 Aug 2024","TimeBeforeDept":"16$24","FromDate":"2024-08-29T23:00:00","ToDate":"2024-08-30T07:00:00"},{"CancellationCharge":100,"CancellationChargeType":2,"PolicyString":"After 07:00 on 30 Aug 2024","TimeBeforeDept":"0$16","FromDate":"2024-08-30T07:00:00","ToDate":"2024-08-31T06:00:00"}]},{"ResultIndex":7,"ArrivalTime":"2024-08-30T18:30:00","AvailableSeats":32,"DepartureTime":"2024-08-30T12:00:00","RouteId":"5000002149901848137","BusType":"Bharat Benz A\/C Sleeper (2+1)","ServiceName":"Seat Seller","TravelName":"VJS Travels","IdProofRequired":false,"IsDropPointMandatory":false,"LiveTrackingAvailable":false,"MTicketEnabled":true,"MaxSeatsPerTicket":6,"OperatorId":29296,"PartialCancellationAllowed":true,"BoardingPointsDetails":[{"CityPointIndex":1,"CityPointLocation":"Majestic","CityPointName":"Majestic","CityPointTime":"2024-08-30T11:10:00"},{"CityPointIndex":2,"CityPointLocation":"AnandRao Circle","CityPointName":"Anand Rao Circle","CityPointTime":"2024-08-30T11:20:00"},{"CityPointIndex":3,"CityPointLocation":"Shanthi Nagar","CityPointName":"Shanthinagar","CityPointTime":"2024-08-30T11:25:00"},{"CityPointIndex":4,"CityPointLocation":"St Johns Hospital","CityPointName":"Others","CityPointTime":"2024-08-30T11:30:00"},{"CityPointIndex":5,"CityPointLocation":"Madiwala","CityPointName":"Madiwala","CityPointTime":"2024-08-30T11:55:00"},{"CityPointIndex":6,"CityPointLocation":"Madiwala Police Station","CityPointName":"Madiwala","CityPointTime":"2024-08-30T12:00:00"},{"CityPointIndex":7,"CityPointLocation":"Silk Board","CityPointName":"Silk Board","CityPointTime":"2024-08-30T12:05:00"},{"CityPointIndex":8,"CityPointLocation":"Electronic City","CityPointName":"Electronic City","CityPointTime":"2024-08-30T12:10:00"},{"CityPointIndex":9,"CityPointLocation":"Bommasandra","CityPointName":"Bommasandra","CityPointTime":"2024-08-30T12:15:00"},{"CityPointIndex":10,"CityPointLocation":"Chandapura","CityPointName":"Chandapura","CityPointTime":"2024-08-30T12:17:00"},{"CityPointIndex":11,"CityPointLocation":"Attibele","CityPointName":"Attibele","CityPointTime":"2024-08-30T12:20:00"},{"CityPointIndex":12,"CityPointLocation":"Hosur","CityPointName":"Hosur","CityPointTime":"2024-08-30T12:55:00"}],"DroppingPointsDetails":[{"CityPointIndex":1,"CityPointLocation":"Kanchipuram","CityPointName":"Kanchipuram","CityPointTime":"2024-08-30T16:45:00"},{"CityPointIndex":2,"CityPointLocation":"Sriperumbathur","CityPointName":"Sriperumbudur","CityPointTime":"2024-08-30T17:35:00"},{"CityPointIndex":3,"CityPointLocation":"Sriperumbathur Bypass","CityPointName":"Sriperumbudur","CityPointTime":"2024-08-30T17:45:00"},{"CityPointIndex":4,"CityPointLocation":"Poonamallee By Pass","CityPointName":"Poonamallee","CityPointTime":"2024-08-30T18:00:00"},{"CityPointIndex":5,"CityPointLocation":"Vanagaram","CityPointName":"Maduravoyal","CityPointTime":"2024-08-30T18:05:00"},{"CityPointIndex":6,"CityPointLocation":"Velapanchavadi","CityPointName":"Velappanchavadi Bus Stop","CityPointTime":"2024-08-30T18:10:00"},{"CityPointIndex":7,"CityPointLocation":"Maduravoyal Mgr University","CityPointName":"Maduravoyal","CityPointTime":"2024-08-30T18:15:00"},{"CityPointIndex":8,"CityPointLocation":"Koyambedu","CityPointName":"Koyambedu","CityPointTime":"2024-08-30T18:30:00"},{"CityPointIndex":9,"CityPointLocation":"Vadapalani","CityPointName":"Vadapalani","CityPointTime":"2024-08-30T18:35:00"},{"CityPointIndex":10,"CityPointLocation":"Ashok Pillar","CityPointName":"Ashok Pillar","CityPointTime":"2024-08-30T18:40:00"},{"CityPointIndex":11,"CityPointLocation":"Guindy","CityPointName":"Guindy","CityPointTime":"2024-08-30T18:45:00"},{"CityPointIndex":12,"CityPointLocation":"Tidel Park","CityPointName":"Tidel Park","CityPointTime":"2024-08-30T18:50:00"},{"CityPointIndex":13,"CityPointLocation":"Tharamani","CityPointName":"Tharamani","CityPointTime":"2024-08-30T18:55:00"},{"CityPointIndex":14,"CityPointLocation":"Velachery","CityPointName":"Velachery","CityPointTime":"2024-08-30T19:00:00"}],"BusPrice":{"CurrencyCode":"INR","BasePrice":1522.50,"Tax":0,"OtherCharges":0,"Discount":0,"PublishedPrice":1522.50,"PublishedPriceRoundedOff":1523,"OfferedPrice":1431.15,"OfferedPriceRoundedOff":1431,"AgentCommission":91.35,"AgentMarkUp":0,"TDS":4.57,"GST":{"CGSTAmount":0,"CGSTRate":0,"CessAmount":0,"CessRate":0,"IGSTAmount":0,"IGSTRate":18,"SGSTAmount":0,"SGSTRate":0,"TaxableAmount":0}},"CancellationPolicies":[{"CancellationCharge":15,"CancellationChargeType":2,"PolicyString":"Till 12:00 on 29 Aug 2024","TimeBeforeDept":"24$-1","FromDate":"2024-07-02T15:29:59","ToDate":"2024-08-29T12:00:00"},{"CancellationCharge":50,"CancellationChargeType":2,"PolicyString":"Between 12:00 on 29 Aug 2024 - 18:00 on 29 Aug 2024","TimeBeforeDept":"18$24","FromDate":"2024-08-29T12:00:00","ToDate":"2024-08-29T18:00:00"},{"CancellationCharge":100,"CancellationChargeType":2,"PolicyString":"After 18:00 on 29 Aug 2024","TimeBeforeDept":"0$18","FromDate":"2024-08-29T18:00:00","ToDate":"2024-08-30T18:30:00"}]},{"ResultIndex":6,"ArrivalTime":"2024-08-30T10:20:00","AvailableSeats":32,"DepartureTime":"2024-08-30T04:30:00","RouteId":"5000002149901848136","BusType":"Bharat Benz A\/C Sleeper (2+1)","ServiceName":"Seat Seller","TravelName":"VJS Travels","IdProofRequired":false,"IsDropPointMandatory":false,"LiveTrackingAvailable":false,"MTicketEnabled":true,"MaxSeatsPerTicket":6,"OperatorId":29296,"PartialCancellationAllowed":true,"BoardingPointsDetails":[{"CityPointIndex":1,"CityPointLocation":"Majestic","CityPointName":"Majestic","CityPointTime":"2024-08-30T04:00:00"},{"CityPointIndex":2,"CityPointLocation":"AnandRao Circle","CityPointName":"Anand Rao Circle","CityPointTime":"2024-08-30T04:10:00"},{"CityPointIndex":3,"CityPointLocation":"Shanthi Nagar","CityPointName":"Shanthinagar","CityPointTime":"2024-08-30T04:15:00"},{"CityPointIndex":4,"CityPointLocation":"St Johns Hospital","CityPointName":"Others","CityPointTime":"2024-08-30T04:20:00"},{"CityPointIndex":5,"CityPointLocation":"Madiwala","CityPointName":"Madiwala","CityPointTime":"2024-08-30T04:25:00"},{"CityPointIndex":6,"CityPointLocation":"Madiwala Police Station","CityPointName":"Madiwala","CityPointTime":"2024-08-30T04:30:00"},{"CityPointIndex":7,"CityPointLocation":"Silk Board","CityPointName":"Silk Board","CityPointTime":"2024-08-30T04:35:00"},{"CityPointIndex":8,"CityPointLocation":"Electronic City","CityPointName":"Electronic City","CityPointTime":"2024-08-30T04:40:00"},{"CityPointIndex":9,"CityPointLocation":"Bommasandra","CityPointName":"Bommasandra","CityPointTime":"2024-08-30T04:45:00"},{"CityPointIndex":10,"CityPointLocation":"Chandapura","CityPointName":"Chandapura","CityPointTime":"2024-08-30T04:47:00"},{"CityPointIndex":11,"CityPointLocation":"Attibele","CityPointName":"Attibele","CityPointTime":"2024-08-30T04:50:00"},{"CityPointIndex":12,"CityPointLocation":"Hosur","CityPointName":"Hosur","CityPointTime":"2024-08-30T05:00:00"}],"DroppingPointsDetails":[{"CityPointIndex":1,"CityPointLocation":"Vaniyambadi","CityPointName":"Perungudi","CityPointTime":"2024-08-30T06:30:00"},{"CityPointIndex":2,"CityPointLocation":"Kanchipuram","CityPointName":"Kanchipuram","CityPointTime":"2024-08-30T09:00:00"},{"CityPointIndex":3,"CityPointLocation":"Sriperumbathur Bypass","CityPointName":"Sriperumbudur","CityPointTime":"2024-08-30T10:00:00"},{"CityPointIndex":4,"CityPointLocation":"Poonamallee By Pass","CityPointName":"Poonamallee","CityPointTime":"2024-08-30T10:05:00"},{"CityPointIndex":5,"CityPointLocation":"Vanagaram","CityPointName":"Maduravoyal","CityPointTime":"2024-08-30T10:07:00"},{"CityPointIndex":6,"CityPointLocation":"Velapanchavadi","CityPointName":"Velappanchavadi Bus Stop","CityPointTime":"2024-08-30T10:09:00"},{"CityPointIndex":7,"CityPointLocation":"Maduravoyal Mgr University","CityPointName":"Maduravoyal","CityPointTime":"2024-08-30T10:10:00"},{"CityPointIndex":8,"CityPointLocation":"Koyambedu","CityPointName":"Koyambedu","CityPointTime":"2024-08-30T10:20:00"},{"CityPointIndex":9,"CityPointLocation":"Vadapalani","CityPointName":"Vadapalani","CityPointTime":"2024-08-30T10:45:00"},{"CityPointIndex":10,"CityPointLocation":"Ashok Pillar","CityPointName":"Ashok Pillar","CityPointTime":"2024-08-30T10:55:00"},{"CityPointIndex":11,"CityPointLocation":"Guindy","CityPointName":"Guindy","CityPointTime":"2024-08-30T11:20:00"},{"CityPointIndex":12,"CityPointLocation":"Tidel Park","CityPointName":"Tidel Park","CityPointTime":"2024-08-30T11:45:00"},{"CityPointIndex":13,"CityPointLocation":"Tharamani","CityPointName":"Tharamani","CityPointTime":"2024-08-30T12:10:00"},{"CityPointIndex":14,"CityPointLocation":"Velachery","CityPointName":"Velachery","CityPointTime":"2024-08-30T12:20:00"}],"BusPrice":{"CurrencyCode":"INR","BasePrice":1575.00,"Tax":0,"OtherCharges":0,"Discount":0,"PublishedPrice":1575.00,"PublishedPriceRoundedOff":1575,"OfferedPrice":1480.50,"OfferedPriceRoundedOff":1481,"AgentCommission":94.50,"AgentMarkUp":0,"TDS":4.72,"GST":{"CGSTAmount":0,"CGSTRate":0,"CessAmount":0,"CessRate":0,"IGSTAmount":0,"IGSTRate":18,"SGSTAmount":0,"SGSTRate":0,"TaxableAmount":0}},"CancellationPolicies":[{"CancellationCharge":15,"CancellationChargeType":2,"PolicyString":"Till 04:30 on 29 Aug 2024","TimeBeforeDept":"24$-1","FromDate":"2024-07-02T15:29:59","ToDate":"2024-08-29T04:30:00"},{"CancellationCharge":50,"CancellationChargeType":2,"PolicyString":"Between 04:30 on 29 Aug 2024 - 10:30 on 29 Aug 2024","TimeBeforeDept":"18$24","FromDate":"2024-08-29T04:30:00","ToDate":"2024-08-29T10:30:00"},{"CancellationCharge":100,"CancellationChargeType":2,"PolicyString":"After 10:30 on 29 Aug 2024","TimeBeforeDept":"0$18","FromDate":"2024-08-29T10:30:00","ToDate":"2024-08-30T10:20:00"}]},{"ResultIndex":5,"ArrivalTime":"2024-08-31T03:30:00","AvailableSeats":32,"DepartureTime":"2024-08-30T20:50:00","RouteId":"5000002149901848135","BusType":"Bharat Benz A\/C Sleeper (2+1)","ServiceName":"Seat Seller","TravelName":"VJS Travels","IdProofRequired":false,"IsDropPointMandatory":false,"LiveTrackingAvailable":false,"MTicketEnabled":true,"MaxSeatsPerTicket":6,"OperatorId":29296,"PartialCancellationAllowed":true,"BoardingPointsDetails":[{"CityPointIndex":1,"CityPointLocation":"Majestic","CityPointName":"Majestic","CityPointTime":"2024-08-30T19:50:00"},{"CityPointIndex":2,"CityPointLocation":"AnandRao Circle","CityPointName":"Anand Rao Circle","CityPointTime":"2024-08-30T19:55:00"},{"CityPointIndex":3,"CityPointLocation":"Shanthi Nagar","CityPointName":"Shanthinagar","CityPointTime":"2024-08-30T20:15:00"},{"CityPointIndex":4,"CityPointLocation":"St Johns Hospital","CityPointName":"Others","CityPointTime":"2024-08-30T20:30:00"},{"CityPointIndex":5,"CityPointLocation":"Madiwala","CityPointName":"Madiwala","CityPointTime":"2024-08-30T20:45:00"},{"CityPointIndex":6,"CityPointLocation":"Madiwala Police Station","CityPointName":"Madiwala","CityPointTime":"2024-08-30T20:50:00"},{"CityPointIndex":7,"CityPointLocation":"Silk Board","CityPointName":"Silk Board","CityPointTime":"2024-08-30T21:00:00"},{"CityPointIndex":8,"CityPointLocation":"Electronic City","CityPointName":"Electronic City","CityPointTime":"2024-08-30T21:15:00"},{"CityPointIndex":9,"CityPointLocation":"Bommasandra","CityPointName":"Bommasandra","CityPointTime":"2024-08-30T21:25:00"},{"CityPointIndex":10,"CityPointLocation":"Chandapura","CityPointName":"Chandapura","CityPointTime":"2024-08-30T21:30:00"},{"CityPointIndex":11,"CityPointLocation":"Attibele","CityPointName":"Attibele","CityPointTime":"2024-08-30T21:35:00"},{"CityPointIndex":12,"CityPointLocation":"Hosur","CityPointName":"Hosur","CityPointTime":"2024-08-30T21:45:00"}],"DroppingPointsDetails":[{"CityPointIndex":1,"CityPointLocation":"Kanchipuram","CityPointName":"Kanchipuram","CityPointTime":"2024-08-31T01:45:00"},{"CityPointIndex":2,"CityPointLocation":"Sriperumbathur Bypass","CityPointName":"Sriperumbudur","CityPointTime":"2024-08-31T02:45:00"},{"CityPointIndex":3,"CityPointLocation":"Poonamallee By Pass","CityPointName":"Poonamallee","CityPointTime":"2024-08-31T03:00:00"},{"CityPointIndex":4,"CityPointLocation":"Vanagaram","CityPointName":"Maduravoyal","CityPointTime":"2024-08-31T03:05:00"},{"CityPointIndex":5,"CityPointLocation":"Velapanchavadi","CityPointName":"Velappanchavadi Bus Stop","CityPointTime":"2024-08-31T03:10:00"},{"CityPointIndex":6,"CityPointLocation":"Maduravoyal Mgr University","CityPointName":"Maduravoyal","CityPointTime":"2024-08-31T03:15:00"},{"CityPointIndex":7,"CityPointLocation":"Koyambedu","CityPointName":"Koyambedu","CityPointTime":"2024-08-31T03:30:00"},{"CityPointIndex":8,"CityPointLocation":"Vadapalani","CityPointName":"Vadapalani","CityPointTime":"2024-08-31T03:35:00"},{"CityPointIndex":9,"CityPointLocation":"Ashok Pillar","CityPointName":"Ashok Pillar","CityPointTime":"2024-08-31T03:40:00"},{"CityPointIndex":10,"CityPointLocation":"Guindy","CityPointName":"Guindy","CityPointTime":"2024-08-31T03:45:00"},{"CityPointIndex":11,"CityPointLocation":"Tidel Park","CityPointName":"Tidel Park","CityPointTime":"2024-08-31T03:50:00"},{"CityPointIndex":12,"CityPointLocation":"Tharamani","CityPointName":"Tharamani","CityPointTime":"2024-08-31T03:55:00"},{"CityPointIndex":13,"CityPointLocation":"Velachery","CityPointName":"Velachery","CityPointTime":"2024-08-31T04:00:00"}],"BusPrice":{"CurrencyCode":"INR","BasePrice":1626.45,"Tax":0,"OtherCharges":0,"Discount":0,"PublishedPrice":1626.45,"PublishedPriceRoundedOff":1626,"OfferedPrice":1528.86,"OfferedPriceRoundedOff":1529,"AgentCommission":97.59,"AgentMarkUp":0,"TDS":4.88,"GST":{"CGSTAmount":0,"CGSTRate":0,"CessAmount":0,"CessRate":0,"IGSTAmount":0,"IGSTRate":18,"SGSTAmount":0,"SGSTRate":0,"TaxableAmount":0}},"CancellationPolicies":[{"CancellationCharge":15,"CancellationChargeType":2,"PolicyString":"Till 20:50 on 29 Aug 2024","TimeBeforeDept":"24$-1","FromDate":"2024-07-02T15:29:59","ToDate":"2024-08-29T20:50:00"},{"CancellationCharge":50,"CancellationChargeType":2,"PolicyString":"Between 20:50 on 29 Aug 2024 - 02:50 on 30 Aug 2024","TimeBeforeDept":"18$24","FromDate":"2024-08-29T20:50:00","ToDate":"2024-08-30T02:50:00"},{"CancellationCharge":100,"CancellationChargeType":2,"PolicyString":"After 02:50 on 30 Aug 2024","TimeBeforeDept":"0$18","FromDate":"2024-08-30T02:50:00","ToDate":"2024-08-31T03:30:00"}]},{"ResultIndex":4,"ArrivalTime":"2024-08-31T07:20:00","AvailableSeats":36,"DepartureTime":"2024-08-30T23:45:00","RouteId":"5000002149900724995","BusType":"A\/C Sleeper (2+1)","ServiceName":"Seat Seller","TravelName":"Jayavin Travels","IdProofRequired":false,"IsDropPointMandatory":false,"LiveTrackingAvailable":false,"MTicketEnabled":true,"MaxSeatsPerTicket":6,"OperatorId":19788,"PartialCancellationAllowed":true,"BoardingPointsDetails":[{"CityPointIndex":1,"CityPointLocation":"Kengeri Bus Terminal","CityPointName":"Kengeri","CityPointTime":"2024-08-30T23:10:00"},{"CityPointIndex":2,"CityPointLocation":"RR Nagar Gate","CityPointName":"Rajarajeshwari Nagar","CityPointTime":"2024-08-30T23:15:00"},{"CityPointIndex":3,"CityPointLocation":"Satellite Bus Stand","CityPointName":"Satellite Bus Stand","CityPointTime":"2024-08-30T23:20:00"},{"CityPointIndex":4,"CityPointLocation":"Kalasipalyam","CityPointName":"Kalasipalyam","CityPointTime":"2024-08-30T23:30:00"},{"CityPointIndex":5,"CityPointLocation":"Shantinagar","CityPointName":"Shanthinagar","CityPointTime":"2024-08-30T23:35:00"},{"CityPointIndex":6,"CityPointLocation":"Christ University","CityPointName":"Christ University","CityPointTime":"2024-08-30T23:40:00"},{"CityPointIndex":7,"CityPointLocation":"Madiwala","CityPointName":"Madiwala","CityPointTime":"2024-08-30T23:45:00"},{"CityPointIndex":8,"CityPointLocation":"Silk board","CityPointName":"Silk Board","CityPointTime":"2024-08-30T23:50:00"},{"CityPointIndex":9,"CityPointLocation":"Electronic city","CityPointName":"Electronic City","CityPointTime":"2024-08-30T23:55:00"},{"CityPointIndex":10,"CityPointLocation":"Bommasandara","CityPointName":"Electronic City","CityPointTime":"2024-08-30T23:58:00"},{"CityPointIndex":11,"CityPointLocation":"Attibelle Toll Gate","CityPointName":"Attibele","CityPointTime":"2024-08-30T23:59:00"}],"DroppingPointsDetails":[{"CityPointIndex":1,"CityPointLocation":"Kanchipuram By Pass","CityPointName":"Kanchipuram Bypass","CityPointTime":"2024-08-31T04:30:00"},{"CityPointIndex":2,"CityPointLocation":"Sriperumbudur Rajiv Memorial","CityPointName":"Sriperumbudur","CityPointTime":"2024-08-31T04:50:00"},{"CityPointIndex":3,"CityPointLocation":"Sriperumbadur","CityPointName":"Sriperumbudur","CityPointTime":"2024-08-31T04:55:00"},{"CityPointIndex":4,"CityPointLocation":"Vellapanchavadi","CityPointName":"Velappanchavadi Bus Stop","CityPointTime":"2024-08-31T05:10:00"},{"CityPointIndex":5,"CityPointLocation":"Ponnamalle","CityPointName":"Poonamallee","CityPointTime":"2024-08-31T05:15:00"},{"CityPointIndex":6,"CityPointLocation":"Maduravayal","CityPointName":"Maduravoyal","CityPointTime":"2024-08-31T05:30:00"},{"CityPointIndex":7,"CityPointLocation":"Koyembedu Omni Bus stand","CityPointName":"Koyambedu","CityPointTime":"2024-08-31T06:01:00"},{"CityPointIndex":8,"CityPointLocation":"Vadapalani","CityPointName":"Vadapalani","CityPointTime":"2024-08-31T06:10:00"},{"CityPointIndex":9,"CityPointLocation":"Ashok Pillar","CityPointName":"Ashok Pillar","CityPointTime":"2024-08-31T06:15:00"},{"CityPointIndex":10,"CityPointLocation":"Ekkatuthangal","CityPointName":"Ekkattuthangal","CityPointTime":"2024-08-31T06:20:00"},{"CityPointIndex":11,"CityPointLocation":"Olympia Tech park","CityPointName":"Ekkattuthangal","CityPointTime":"2024-08-31T06:25:00"},{"CityPointIndex":12,"CityPointLocation":"Guindy Railway Statioin","CityPointName":"Guindy","CityPointTime":"2024-08-31T06:25:00"},{"CityPointIndex":13,"CityPointLocation":"Anna University","CityPointName":"Anna University","CityPointTime":"2024-08-31T06:30:00"},{"CityPointIndex":14,"CityPointLocation":"IIT Chennai","CityPointName":"Iit Chennai","CityPointTime":"2024-08-31T06:30:00"},{"CityPointIndex":15,"CityPointLocation":"Mathya Kailash","CityPointName":"Madhya Kailash","CityPointTime":"2024-08-31T06:35:00"},{"CityPointIndex":16,"CityPointLocation":"Tidel Park","CityPointName":"Tidel Park","CityPointTime":"2024-08-31T06:40:00"},{"CityPointIndex":17,"CityPointLocation":"SRP Tools","CityPointName":"SRP Tools","CityPointTime":"2024-08-31T06:45:00"},{"CityPointIndex":18,"CityPointLocation":"Perungudi","CityPointName":"Perungudi","CityPointTime":"2024-08-31T06:50:00"},{"CityPointIndex":19,"CityPointLocation":"Thuraipakkam","CityPointName":"Thuraipakkam","CityPointTime":"2024-08-31T06:55:00"},{"CityPointIndex":20,"CityPointLocation":"Karappakam","CityPointName":"Karappakkam","CityPointTime":"2024-08-31T07:00:00"},{"CityPointIndex":21,"CityPointLocation":"Sholinganallur","CityPointName":"Sholinganallur","CityPointTime":"2024-08-31T07:05:00"},{"CityPointIndex":22,"CityPointLocation":"Satyabama University","CityPointName":"Sathyabama University","CityPointTime":"2024-08-31T07:10:00"},{"CityPointIndex":23,"CityPointLocation":"Navalur","CityPointName":"Navalur","CityPointTime":"2024-08-31T07:15:00"},{"CityPointIndex":24,"CityPointLocation":"Siruseri","CityPointName":"SIPCOT Siruseri","CityPointTime":"2024-08-31T07:20:00"}],"BusPrice":{"CurrencyCode":"INR","BasePrice":1890.00,"Tax":0,"OtherCharges":0,"Discount":0,"PublishedPrice":1890.00,"PublishedPriceRoundedOff":1890,"OfferedPrice":1776.60,"OfferedPriceRoundedOff":1777,"AgentCommission":113.40,"AgentMarkUp":0,"TDS":5.67,"GST":{"CGSTAmount":0,"CGSTRate":0,"CessAmount":0,"CessRate":0,"IGSTAmount":0,"IGSTRate":18,"SGSTAmount":0,"SGSTRate":0,"TaxableAmount":0}},"CancellationPolicies":[{"CancellationCharge":15,"CancellationChargeType":2,"PolicyString":"Till 11:45 on 29 Aug 2024","TimeBeforeDept":"36$-1","FromDate":"2024-07-02T15:29:59","ToDate":"2024-08-29T11:45:00"},{"CancellationCharge":30,"CancellationChargeType":2,"PolicyString":"Between 11:45 on 29 Aug 2024 - 23:45 on 29 Aug 2024","TimeBeforeDept":"24$36","FromDate":"2024-08-29T11:45:00","ToDate":"2024-08-29T23:45:00"},{"CancellationCharge":60,"CancellationChargeType":2,"PolicyString":"Between 23:45 on 29 Aug 2024 - 05:45 on 30 Aug 2024","TimeBeforeDept":"18$24","FromDate":"2024-08-29T23:45:00","ToDate":"2024-08-30T05:45:00"},{"CancellationCharge":100,"CancellationChargeType":2,"PolicyString":"After 05:45 on 30 Aug 2024","TimeBeforeDept":"0$18","FromDate":"2024-08-30T05:45:00","ToDate":"2024-08-31T07:20:00"}]},{"ResultIndex":2,"ArrivalTime":"2024-08-31T04:30:00","AvailableSeats":30,"DepartureTime":"2024-08-30T22:30:00","RouteId":"1000002149901472942","BusType":"A\/C Sleeper (2+1)","ServiceName":"Seat Seller","TravelName":"YBM Travels(BLM)","IdProofRequired":false,"IsDropPointMandatory":false,"LiveTrackingAvailable":false,"MTicketEnabled":true,"MaxSeatsPerTicket":6,"OperatorId":11046,"PartialCancellationAllowed":true,"BoardingPointsDetails":[{"CityPointIndex":1,"CityPointLocation":"Marathahalli","CityPointName":"Marathahalli","CityPointTime":"2024-08-30T21:35:00"},{"CityPointIndex":2,"CityPointLocation":"Bellandur","CityPointName":"Bellandur","CityPointTime":"2024-08-30T21:45:00"},{"CityPointIndex":3,"CityPointLocation":"HSR Layout","CityPointName":"HSR Layout","CityPointTime":"2024-08-30T22:00:00"},{"CityPointIndex":4,"CityPointLocation":"Madiwala","CityPointName":"Madiwala","CityPointTime":"2024-08-30T22:30:00"},{"CityPointIndex":5,"CityPointLocation":"Silk Board","CityPointName":"Silk Board","CityPointTime":"2024-08-30T22:40:00"},{"CityPointIndex":6,"CityPointLocation":"Electronic City.","CityPointName":"Electronic City","CityPointTime":"2024-08-30T22:50:00"},{"CityPointIndex":7,"CityPointLocation":"Bommasandra","CityPointName":"Bommasandra","CityPointTime":"2024-08-30T22:55:00"},{"CityPointIndex":8,"CityPointLocation":"Attibele","CityPointName":"Attibele","CityPointTime":"2024-08-30T23:05:00"}],"DroppingPointsDetails":[{"CityPointIndex":1,"CityPointLocation":"Poonamalle Bypass","CityPointName":"Poonamallee","CityPointTime":"2024-08-31T04:15:00"},{"CityPointIndex":2,"CityPointLocation":"Maduravoyal","CityPointName":"Maduravoyal","CityPointTime":"2024-08-31T04:20:00"},{"CityPointIndex":3,"CityPointLocation":"Maduravoyal - MGR University","CityPointName":"Maduravoyal","CityPointTime":"2024-08-31T04:25:00"},{"CityPointIndex":4,"CityPointLocation":"Koyambedu(Van Pickup)","CityPointName":"Koyambedu","CityPointTime":"2024-08-31T04:30:00"},{"CityPointIndex":5,"CityPointLocation":"Koyambedu CMBT","CityPointName":"Koyambedu","CityPointTime":"2024-08-31T04:35:00"},{"CityPointIndex":6,"CityPointLocation":"VADAPALANI.","CityPointName":"Vadapalani","CityPointTime":"2024-08-31T04:40:00"},{"CityPointIndex":7,"CityPointLocation":"ASHOK PILLAR.","CityPointName":"Ashok Pillar","CityPointTime":"2024-08-31T04:45:00"},{"CityPointIndex":8,"CityPointLocation":"GUINDY  Indian bank Atm","CityPointName":"Guindy","CityPointTime":"2024-08-31T04:50:00"},{"CityPointIndex":9,"CityPointLocation":"EKKATTUTHANGAL- OLYMPIA","CityPointName":"Ekkattuthangal","CityPointTime":"2024-08-31T04:50:00"},{"CityPointIndex":10,"CityPointLocation":"SAIDAPET Bus Stand","CityPointName":"Saidapet","CityPointTime":"2024-08-31T04:55:00"},{"CityPointIndex":11,"CityPointLocation":"ANNA UNIVERSITY","CityPointName":"Anna University","CityPointTime":"2024-08-31T04:57:00"},{"CityPointIndex":12,"CityPointLocation":"MADHYA KAILASH - Railway Station","CityPointName":"Madhya Kailash","CityPointTime":"2024-08-31T05:00:00"},{"CityPointIndex":13,"CityPointLocation":"TIDEL PARK","CityPointName":"Tidel Park","CityPointTime":"2024-08-31T05:03:00"},{"CityPointIndex":14,"CityPointLocation":"SRP TOOLS","CityPointName":"SRP Tools","CityPointTime":"2024-08-31T05:05:00"},{"CityPointIndex":15,"CityPointLocation":"Perungudi","CityPointName":"Perungudi","CityPointTime":"2024-08-31T05:10:00"},{"CityPointIndex":16,"CityPointLocation":"Thuraipakkam","CityPointName":"Thuraipakkam","CityPointTime":"2024-08-31T05:13:00"},{"CityPointIndex":17,"CityPointLocation":"Shollinganallur","CityPointName":"Sholinganallur","CityPointTime":"2024-08-31T05:15:00"},{"CityPointIndex":18,"CityPointLocation":"SATHYABHAMA UNIVERSITY","CityPointName":"Sathyabama University","CityPointTime":"2024-08-31T05:20:00"},{"CityPointIndex":19,"CityPointLocation":"NAVALUR TOLL","CityPointName":"Navalur","CityPointTime":"2024-08-31T05:24:00"},{"CityPointIndex":20,"CityPointLocation":"Navalur","CityPointName":"Navalur","CityPointTime":"2024-08-31T05:27:00"},{"CityPointIndex":21,"CityPointLocation":"SIRUSERI","CityPointName":"SIPCOT Siruseri","CityPointTime":"2024-08-31T05:30:00"}],"BusPrice":{"CurrencyCode":"INR","BasePrice":1942.50,"Tax":0,"OtherCharges":0,"Discount":0,"PublishedPrice":1942.50,"PublishedPriceRoundedOff":1943,"OfferedPrice":1825.95,"OfferedPriceRoundedOff":1826,"AgentCommission":116.55,"AgentMarkUp":0,"TDS":5.83,"GST":{"CGSTAmount":0,"CGSTRate":0,"CessAmount":0,"CessRate":0,"IGSTAmount":0,"IGSTRate":18,"SGSTAmount":0,"SGSTRate":0,"TaxableAmount":0}},"CancellationPolicies":[{"CancellationCharge":15,"CancellationChargeType":2,"PolicyString":"Till 10:30 on 29 Aug 2024","TimeBeforeDept":"36$-1","FromDate":"2024-07-02T15:29:59","ToDate":"2024-08-29T10:30:00"},{"CancellationCharge":50,"CancellationChargeType":2,"PolicyString":"Between 10:30 on 29 Aug 2024 - 06:30 on 30 Aug 2024","TimeBeforeDept":"16$36","FromDate":"2024-08-29T10:30:00","ToDate":"2024-08-30T06:30:00"},{"CancellationCharge":100,"CancellationChargeType":2,"PolicyString":"After 06:30 on 30 Aug 2024","TimeBeforeDept":"0$16","FromDate":"2024-08-30T06:30:00","ToDate":"2024-08-31T04:30:00"}]},{"ResultIndex":3,"ArrivalTime":"2024-08-30T13:30:00","AvailableSeats":23,"DepartureTime":"2024-08-30T07:00:00","RouteId":"1000002149902339483","BusType":"A\/C Sleeper (2+1)","ServiceName":"Seat Seller","TravelName":"YBM Travels(BLM)","IdProofRequired":false,"IsDropPointMandatory":false,"LiveTrackingAvailable":false,"MTicketEnabled":true,"MaxSeatsPerTicket":6,"OperatorId":11046,"PartialCancellationAllowed":true,"BoardingPointsDetails":[{"CityPointIndex":1,"CityPointLocation":"Marathahalli","CityPointName":"Marathahalli","CityPointTime":"2024-08-30T06:35:00"},{"CityPointIndex":2,"CityPointLocation":"Bellandur","CityPointName":"Bellandur","CityPointTime":"2024-08-30T06:45:00"},{"CityPointIndex":3,"CityPointLocation":"HSR Layout","CityPointName":"HSR Layout","CityPointTime":"2024-08-30T06:50:00"},{"CityPointIndex":4,"CityPointLocation":"Madiwala","CityPointName":"Madiwala","CityPointTime":"2024-08-30T07:00:00"},{"CityPointIndex":5,"CityPointLocation":"Silk Board","CityPointName":"Silk Board","CityPointTime":"2024-08-30T07:10:00"},{"CityPointIndex":6,"CityPointLocation":"Electronic City.","CityPointName":"Electronic City","CityPointTime":"2024-08-30T07:25:00"},{"CityPointIndex":7,"CityPointLocation":"Bommasandra","CityPointName":"Bommasandra","CityPointTime":"2024-08-30T07:30:00"},{"CityPointIndex":8,"CityPointLocation":"Narayana Hrudayalaya Hospital","CityPointName":"Harapanapalya","CityPointTime":"2024-08-30T07:35:00"},{"CityPointIndex":9,"CityPointLocation":"Attibele","CityPointName":"Attibele","CityPointTime":"2024-08-30T07:45:00"}],"DroppingPointsDetails":[{"CityPointIndex":1,"CityPointLocation":"Kanchipuram Bypass","CityPointName":"Kanchipuram Bypass","CityPointTime":"2024-08-30T12:30:00"},{"CityPointIndex":2,"CityPointLocation":"Sriperumbudur - Rajiv Gandhi Memorial","CityPointName":"Sriperumbudur","CityPointTime":"2024-08-30T12:45:00"},{"CityPointIndex":3,"CityPointLocation":"Sriperumbudur - Tollgate","CityPointName":"Sriperumbudur","CityPointTime":"2024-08-30T12:50:00"},{"CityPointIndex":4,"CityPointLocation":"Poonamalle Bypass","CityPointName":"Poonamallee","CityPointTime":"2024-08-30T13:15:00"},{"CityPointIndex":5,"CityPointLocation":"Maduravoyal - MGR University","CityPointName":"Maduravoyal","CityPointTime":"2024-08-30T13:25:00"},{"CityPointIndex":6,"CityPointLocation":"Koyambedu(Van Pickup)","CityPointName":"Koyambedu","CityPointTime":"2024-08-30T13:30:00"},{"CityPointIndex":7,"CityPointLocation":"Koyambedu CMBT","CityPointName":"Koyambedu","CityPointTime":"2024-08-30T13:35:00"},{"CityPointIndex":8,"CityPointLocation":"VADAPALANI.","CityPointName":"Vadapalani","CityPointTime":"2024-08-30T13:40:00"},{"CityPointIndex":9,"CityPointLocation":"ASHOK PILLAR.","CityPointName":"Ashok Pillar","CityPointTime":"2024-08-30T13:45:00"},{"CityPointIndex":10,"CityPointLocation":"EKKATTUTHANGAL- OLYMPIA","CityPointName":"Ekkattuthangal","CityPointTime":"2024-08-30T13:50:00"},{"CityPointIndex":11,"CityPointLocation":"GUINDY  Indian bank Atm","CityPointName":"Guindy","CityPointTime":"2024-08-30T13:55:00"},{"CityPointIndex":12,"CityPointLocation":"SAIDAPET Bus Stand","CityPointName":"Saidapet","CityPointTime":"2024-08-30T14:00:00"},{"CityPointIndex":13,"CityPointLocation":"ANNA UNIVERSITY","CityPointName":"Anna University","CityPointTime":"2024-08-30T14:05:00"},{"CityPointIndex":14,"CityPointLocation":"MADHYA KAILASH - Railway Station","CityPointName":"Madhya Kailash","CityPointTime":"2024-08-30T14:07:00"},{"CityPointIndex":15,"CityPointLocation":"TIDEL PARK","CityPointName":"Tidel Park","CityPointTime":"2024-08-30T14:10:00"},{"CityPointIndex":16,"CityPointLocation":"SRP TOOLS","CityPointName":"SRP Tools","CityPointTime":"2024-08-30T14:15:00"},{"CityPointIndex":17,"CityPointLocation":"Perungudi","CityPointName":"Perungudi","CityPointTime":"2024-08-30T14:20:00"},{"CityPointIndex":18,"CityPointLocation":"Thuraipakkam","CityPointName":"Thuraipakkam","CityPointTime":"2024-08-30T14:23:00"},{"CityPointIndex":19,"CityPointLocation":"Shollinganallur","CityPointName":"Sholinganallur","CityPointTime":"2024-08-30T14:25:00"},{"CityPointIndex":20,"CityPointLocation":"SATHYABHAMA UNIVERSITY","CityPointName":"Sathyabama University","CityPointTime":"2024-08-30T14:30:00"},{"CityPointIndex":21,"CityPointLocation":"Navalur Toll","CityPointName":"Navalur","CityPointTime":"2024-08-30T14:35:00"},{"CityPointIndex":22,"CityPointLocation":"Navalur","CityPointName":"Navalur","CityPointTime":"2024-08-30T14:40:00"},{"CityPointIndex":23,"CityPointLocation":"SIRUSERI","CityPointName":"SIPCOT Siruseri","CityPointTime":"2024-08-30T14:45:00"}],"BusPrice":{"CurrencyCode":"INR","BasePrice":2257.50,"Tax":0,"OtherCharges":0,"Discount":0,"PublishedPrice":2257.50,"PublishedPriceRoundedOff":2258,"OfferedPrice":2122.05,"OfferedPriceRoundedOff":2122,"AgentCommission":135.45,"AgentMarkUp":0,"TDS":6.77,"GST":{"CGSTAmount":0,"CGSTRate":0,"CessAmount":0,"CessRate":0,"IGSTAmount":0,"IGSTRate":18,"SGSTAmount":0,"SGSTRate":0,"TaxableAmount":0}},"CancellationPolicies":[{"CancellationCharge":15,"CancellationChargeType":2,"PolicyString":"Till 19:00 on 28 Aug 2024","TimeBeforeDept":"36$-1","FromDate":"2024-07-02T15:29:59","ToDate":"2024-08-28T19:00:00"},{"CancellationCharge":50,"CancellationChargeType":2,"PolicyString":"Between 19:00 on 28 Aug 2024 - 15:00 on 29 Aug 2024","TimeBeforeDept":"16$36","FromDate":"2024-08-28T19:00:00","ToDate":"2024-08-29T15:00:00"},{"CancellationCharge":100,"CancellationChargeType":2,"PolicyString":"After 15:00 on 29 Aug 2024","TimeBeforeDept":"0$16","FromDate":"2024-08-29T15:00:00","ToDate":"2024-08-30T13:30:00"}]},{"ResultIndex":9,"ArrivalTime":"2024-08-31T05:50:00","AvailableSeats":36,"DepartureTime":"2024-08-30T23:45:00","RouteId":"5000002149903118305","BusType":"A\/C Sleeper (2+1)","ServiceName":"Seat Seller","TravelName":"(SBLT) Shri Bhagiyalakshimi Travels (MAARA)","IdProofRequired":false,"IsDropPointMandatory":false,"LiveTrackingAvailable":false,"MTicketEnabled":true,"MaxSeatsPerTicket":6,"OperatorId":17597,"PartialCancellationAllowed":true,"BoardingPointsDetails":[{"CityPointIndex":1,"CityPointLocation":"Kalasipalayam","CityPointName":"Kalasipalyam","CityPointTime":"2024-08-30T23:15:00"},{"CityPointIndex":2,"CityPointLocation":"Santhi Nagar","CityPointName":"Basaveshwara Nagar","CityPointTime":"2024-08-30T23:20:00"},{"CityPointIndex":3,"CityPointLocation":"Madiwala","CityPointName":"Madiwala","CityPointTime":"2024-08-30T23:45:00"},{"CityPointIndex":4,"CityPointLocation":"Silk Board","CityPointName":"Silk Board","CityPointTime":"2024-08-30T23:55:00"},{"CityPointIndex":5,"CityPointLocation":"Electronic City","CityPointName":"Electronic City","CityPointTime":"2024-08-31T00:05:00"},{"CityPointIndex":6,"CityPointLocation":"Boomasandra","CityPointName":"Bommasandra","CityPointTime":"2024-08-31T00:10:00"},{"CityPointIndex":7,"CityPointLocation":"Chandapura","CityPointName":"Chandapura","CityPointTime":"2024-08-31T00:15:00"},{"CityPointIndex":8,"CityPointLocation":"Attibele Toll","CityPointName":"Attibele","CityPointTime":"2024-08-31T00:25:00"},{"CityPointIndex":9,"CityPointLocation":"Hosur","CityPointName":"Hosur","CityPointTime":"2024-08-31T00:35:00"}],"DroppingPointsDetails":[{"CityPointIndex":1,"CityPointLocation":"Kanchipuram","CityPointName":"Kanchipuram","CityPointTime":"2024-08-31T04:35:00"},{"CityPointIndex":2,"CityPointLocation":"Sunguvarchatram Bypass","CityPointName":"Others","CityPointTime":"2024-08-31T04:50:00"},{"CityPointIndex":3,"CityPointLocation":"Saint Gobain","CityPointName":"Others","CityPointTime":"2024-08-31T04:55:00"},{"CityPointIndex":4,"CityPointLocation":"Sri Perambathur Tollgate Plaza","CityPointName":"Others","CityPointTime":"2024-08-31T05:00:00"},{"CityPointIndex":5,"CityPointLocation":"Sri Peramabathur","CityPointName":"Others","CityPointTime":"2024-08-31T05:05:00"},{"CityPointIndex":6,"CityPointLocation":"Saveetha Medical College","CityPointName":"Velappanchavadi Bus Stop","CityPointTime":"2024-08-31T05:10:00"},{"CityPointIndex":7,"CityPointLocation":"Poonamallee(vanpickup)","CityPointName":"Poonamallee","CityPointTime":"2024-08-31T05:15:00"},{"CityPointIndex":8,"CityPointLocation":"Poonamallee Ambedkar Statue(vanpickup)","CityPointName":"Poonamallee","CityPointTime":"2024-08-31T05:20:00"},{"CityPointIndex":9,"CityPointLocation":"Poonamallee Acs Medical Hospital(vanpickup)","CityPointName":"Poonamallee","CityPointTime":"2024-08-31T05:25:00"},{"CityPointIndex":10,"CityPointLocation":"Velappanchavadivanpickup)","CityPointName":"Velappanchavadi Bus Stop","CityPointTime":"2024-08-31T05:30:00"},{"CityPointIndex":11,"CityPointLocation":"Maduravoyal (erikarai Stop)vanpickup)","CityPointName":"Maduravoyal","CityPointTime":"2024-08-31T05:35:00"},{"CityPointIndex":12,"CityPointLocation":"Maduravoyal (Erikarai Stop)vanpickup)","CityPointName":"Maduravoyal","CityPointTime":"2024-08-31T05:40:00"},{"CityPointIndex":13,"CityPointLocation":"Koyambedu (SBLT Office)(van pickup)","CityPointName":"Koyambedu","CityPointTime":"2024-08-31T05:50:00"}],"BusPrice":{"CurrencyCode":"INR","BasePrice":5248.95,"Tax":0,"OtherCharges":0,"Discount":0,"PublishedPrice":5248.95,"PublishedPriceRoundedOff":5249,"OfferedPrice":4934.01,"OfferedPriceRoundedOff":4934,"AgentCommission":314.94,"AgentMarkUp":0,"TDS":15.75,"GST":{"CGSTAmount":0,"CGSTRate":0,"CessAmount":0,"CessRate":0,"IGSTAmount":0,"IGSTRate":18,"SGSTAmount":0,"SGSTRate":0,"TaxableAmount":0}},"CancellationPolicies":[{"CancellationCharge":10,"CancellationChargeType":2,"PolicyString":"Till 11:45 on 29 Aug 2024","TimeBeforeDept":"36$-1","FromDate":"2024-07-02T15:29:59","ToDate":"2024-08-29T11:45:00"},{"CancellationCharge":10,"CancellationChargeType":2,"PolicyString":"Between 11:45 on 29 Aug 2024 - 08:45 on 30 Aug 2024","TimeBeforeDept":"15$36","FromDate":"2024-08-29T11:45:00","ToDate":"2024-08-30T08:45:00"},{"CancellationCharge":100,"CancellationChargeType":2,"PolicyString":"After 08:45 on 30 Aug 2024","TimeBeforeDept":"0$15","FromDate":"2024-08-30T08:45:00","ToDate":"2024-08-31T05:50:00"}]}]}}